TQOLU/__init__.py
TQOLU/other_module.py
TQOLU-0.1.dist-info/LICENSE
TQOLU-0.1.dist-info/METADATA
TQOLU-0.1.dist-info/WHEEL
TQOLU-0.1.dist-info/top_level.txt
TQOLU-0.1.dist-info/RECORD
