Metadata-Version: 2.1
Name: TQOLU
Version: 0.1
Summary: Adds many utilities for easy Python coding.
Home-page: https://github.com/Talklet123/TQOLU.git
Author: Talklet
Author-email: develepor1234567890234@yahoo.com
License: MIT
Platform: UNKNOWN
License-File: LICENSE
